Metadata-Version: 1.0
Name: bio-genome
Version: 0.1
Summary: genomes
Home-page: UNKNOWN
Author: Gianluca Balestra
Author-email: gbalestra6@gmail.com
License: UNKNOWN
Platform: UNKNOWN
